AmazonPay/__init__.py
AmazonPay/client.py
AmazonPayClient-2.0.1.dist-info/LICENSE
AmazonPayClient-2.0.1.dist-info/METADATA
AmazonPayClient-2.0.1.dist-info/NOTICE
AmazonPayClient-2.0.1.dist-info/WHEEL
AmazonPayClient-2.0.1.dist-info/top_level.txt
AmazonPayClient-2.0.1.dist-info/RECORD
