Metadata-Version: 2.1
Name: AmazonPayClient
Version: 2.0.1
Summary: A non-official Amazon Pay Python SDK
Home-page: https://github.com/wangrunbo/amazon-pay-api-sdk-python
Author: Wang Runbo
Author-email: wangrunbo921@gmail.com
License: Apache License version 2.0, January 2004
Keywords: Amazon,Payments,Python,API,SDK
Platform: UNKNOWN
Classifier: Development Status :: 5 - Production/Stable
Classifier: Intended Audience :: Developers
Classifier: License :: OSI Approved :: Apache Software License
Classifier: Natural Language :: English
Classifier: Operating System :: OS Independent
Classifier: Programming Language :: Python
Classifier: Programming Language :: Python :: 3
Classifier: Programming Language :: Python :: 3 :: Only
Classifier: Programming Language :: Python :: 3.5
Classifier: Programming Language :: Python :: 3.6
Classifier: Programming Language :: Python :: 3.7
Classifier: Programming Language :: Python :: 3.8
Classifier: Programming Language :: Python :: 3.9
Classifier: Programming Language :: Python :: 3.10
Classifier: Programming Language :: Python :: 3.11
Classifier: Programming Language :: Python :: 3.12
Classifier: Topic :: Software Development :: Libraries
Classifier: Topic :: Software Development :: Libraries :: Python Modules
License-File: LICENSE
License-File: NOTICE
Requires-Dist: requests (>=2.28.1)
Requires-Dist: pycryptodome (>=3.16.0)
